{"frames":{"sprite40":{"frame":{"x":10,"y":0,"w":122,"h":140},"rotated":false,"trimmed":false,"spriteSourceSize":{"x":0,"y":0,"w":122,"h":140},"sourceSize":{"w":122,"h":140}},"sprite41":{"frame":{"x":570,"y":4,"w":139,"h":140},"rotated":false,"trimmed":false,"spriteSourceSize":{"x":0,"y":0,"w":139,"h":140},"sourceSize":{"w":139,"h":140}},"sprite42":{"frame":{"x":371,"y":9,"w":130,"h":131},"rotated":false,"trimmed":false,"spriteSourceSize":{"x":0,"y":0,"w":130,"h":131},"sourceSize":{"w":130,"h":131}},"sprite43":{"frame":{"x":177,"y":14,"w":149,"h":130},"rotated":false,"trimmed":false,"spriteSourceSize":{"x":0,"y":0,"w":149,"h":130},"sourceSize":{"w":149,"h":130}},"sprite44":{"frame":{"x":12,"y":150,"w":142,"h":212},"rotated":false,"trimmed":false,"spriteSourceSize":{"x":0,"y":0,"w":142,"h":212},"sourceSize":{"w":142,"h":212}},"sprite45":{"frame":{"x":226,"y":174,"w":127,"h":183},"rotated":false,"trimmed":false,"spriteSourceSize":{"x":0,"y":0,"w":127,"h":183},"sourceSize":{"w":127,"h":183}},"sprite46":{"frame":{"x":400,"y":195,"w":170,"h":138},"rotated":false,"trimmed":false,"spriteSourceSize":{"x":0,"y":0,"w":170,"h":138},"sourceSize":{"w":170,"h":138}},"sprite47":{"frame":{"x":0,"y":368,"w":166,"h":188},"rotated":false,"trimmed":false,"spriteSourceSize":{"x":0,"y":0,"w":166,"h":188},"sourceSize":{"w":166,"h":188}},"sprite48":{"frame":{"x":434,"y":389,"w":156,"h":159},"rotated":false,"trimmed":false,"spriteSourceSize":{"x":0,"y":0,"w":156,"h":159},"sourceSize":{"w":156,"h":159}},"sprite49":{"frame":{"x":210,"y":418,"w":176,"h":104},"rotated":false,"trimmed":false,"spriteSourceSize":{"x":0,"y":0,"w":176,"h":104},"sourceSize":{"w":176,"h":104}}},"meta":{"app":"https://www.leshylabs.com/apps/sstool/","version":"Leshy SpriteSheet Tool v0.8.4","image":"spritesheet.png","size":{"w":709,"h":556},"scale":1}}